[
  {
    "id": "1096951954622480385",
    "book": "firstSamuel                        ",
    "chapter": "13",
    "verse": "5",
    "text": "非利士人 聚集，要與 以色列人 爭戰，有車 三萬輛，馬兵 六 千，步兵 像 海 邊 的沙 那樣多，就上來在伯‧亞文 東邊 的密抹 安營。                                                                                                                                                                                                                                                                                                                                                                                                                                                                                                                                                                                                                                                                                                                                                                                                                                                        "
  }
]