[
  {
    "id": "1096952333769539585",
    "book": "luke                               ",
    "chapter": "20",
    "verse": "44",
    "text": "大衛 既 稱 他 為主，他怎麼 又 是 大衛 的子孫呢？」                                                                                                                                                                                                                                                                                                                                                                                                                                                                                                                                                                                                                                                                                                                                                                                                                                                                                                                                                                 "
  }
]