[
  {
    "id": "1137773000653635585",
    "book": "psalms                             ",
    "chapter": "79",
    "verse": "7",
    "text": "因為 他們吞了 雅各，把 他的住處 變為荒場。                                                                                                                                                                                                                                                                                                                                                                                                                                                                                                                                                                                                                                                                                                                                                                                                                                                                                                                                                                           "
  }
]