[
  {
    "id": "1096952114308579329",
    "book": "job                                ",
    "chapter": "8",
    "verse": "18",
    "text": "他若 從本地 被拔出，那地就不認識 他，說：我沒有 見過你。                                                                                                                                                                                                                                                                                                                                                                                                                                                                                                                                                                                                                                                                                                                                                                                                                                                                                                                                                      "
  }
]