[
  {
    "id": "1096952103067975681",
    "book": "firstChronicles                    ",
    "chapter": "6",
    "verse": "66",
    "text": "哥轄 族 中有幾家 在以法蓮 支派 的地 中也得了 城邑，                                                                                                                                                                                                                                                                                                                                                                                                                                                                                                                                                                                                                                                                                                                                                                                                                                                                                                                                                               "
  }
]