[
  {
    "id": "1138147997648093186",
    "book": "matthew                            ",
    "chapter": "6",
    "verse": "20",
    "text": "Sammelt euch aber Schatze im Himmel, da sie weder Motten noch Rost fressen, und da die Diebe nicht nach graben noch stehlen.                                                                                                                                                                                                                                                                                                                                                                                                                                                                                                                                                                                                                                                                                                                                                                                                                                                                                                            "
  }
]