[
  {
    "id": "1138150332164276226",
    "book": "acts                               ",
    "chapter": "20",
    "verse": "23",
    "text": "ohne daß der Heilige Geist in alien Stadten bezeuget und spricht: Bande und Trubsal warten mein daselbst.                                                                                                                                                                                                                                                                                                                                                                                                                                                                                                                                                                                                                                                                                                                                                                                                                                                                                                                              "
  }
]