[
  {
    "id": "1096952109093552129",
    "book": "secondChronicles                   ",
    "chapter": "31",
    "verse": "13",
    "text": "耶歇、亞撒細雅、拿哈、亞撒黑、耶利末、約撒拔、以列、伊斯瑪基雅、瑪哈、比拿雅 都是督理，在歌楠雅 和他兄弟 示每 的手下，是希西家 王 和管理　神 殿 的亞撒利雅 所派的。                                                                                                                                                                                                                                                                                                                                                                                                                                                                                                                                                                                                                                                                                                                                                                                        "
  }
]