[
  {
    "id": "1138141218351775746",
    "book": "job                                ",
    "chapter": "37",
    "verse": "4",
    "text": "Dem nach brullet der Donner, und er donnert mit seinem graven Schall, und wenn sein Donner gehoret wird, kann man's nicht aufhalten.                                                                                                                                                                                                                                                                                                                                                                                                                                                                                                                                                                                                                                                                                                                                                                                                                                                                                                    "
  }
]