[
  {
    "id": "1096951417739411457",
    "book": "genesis                            ",
    "chapter": "13",
    "verse": "18",
    "text": "亞伯蘭 就搬了帳棚，來 到希伯崙 幔利 的橡樹 那裡 居住，在那裡 為耶和華 築 了一座壇。                                                                                                                                                                                                                                                                                                                                                                                                                                                                                                                                                                                                                                                                                                                                                                                                                                                                                                                "
  }
]