[
  {
    "id": "1138140297489121282",
    "book": "ezra                               ",
    "chapter": "4",
    "verse": "11",
    "text": "Und dies ist der Inhalt des Briefes, den sie zu dem Konige Arthahsastha sandten: Deine Knechte, die Manner diesseit des Wassers und in Kanaan.                                                                                                                                                                                                                                                                                                                                                                                                                                                                                                                                                                                                                                                                                                                                                                                                                                                                                          "
  }
]