[
  {
    "id": "1096951658070900737",
    "book": "exodus                             ",
    "chapter": "34",
    "verse": "9",
    "text": "說：「主啊，我若 在你眼前 蒙 恩， 求你 在我們中間 同行，因為 這是 硬著 頸項的 百姓。又求你赦免 我們的罪孽 和罪惡，以我們為你的產業。」                                                                                                                                                                                                                                                                                                                                                                                                                                                                                                                                                                                                                                                                                                                                                                                                                                     "
  }
]