[
  {
    "id": "1096952329877553153",
    "book": "luke                               ",
    "chapter": "1",
    "verse": "48",
    "text": "因為 他顧念 他 使女 的卑微； 從 今以後，萬 代 要稱我 有福。                                                                                                                                                                                                                                                                                                                                                                                                                                                                                                                                                                                                                                                                                                                                                                                                                                                                                                                                                    "
  }
]