[
  {
    "id": "1138148047180890114",
    "book": "matthew                            ",
    "chapter": "9",
    "verse": "15",
    "text": "Jesus sprach zu ihnen: Wie konnen die Hochzeitleute Leid tragen, solange der Brautigam bei ihnen ist? Es wird aber die Zeit kommen, dafi der Brautigam von ihnen genommen wird; alsdann werden sie fasten.                                                                                                                                                                                                                                                                                                                                                                                                                                                                                                                                                                                                                                                                                                                                                                                                                              "
  }
]