[
  {
    "id": "888945040837836801",
    "book": "judges                             ",
    "chapter": "16",
    "verse": "11",
    "text": " And he said unto her, If they bind me fast with new ropes that never were occupied, then shall I be weak, and be as another man.                                                                                                                                                                                                                                                                                                                                                                                                                                                                                                                                                                                                                                                                                                                                                                                                                                                                                                       "
  }
]