[
  {
    "id": "888950932797915137",
    "book": "isaiah                             ",
    "chapter": "14",
    "verse": "18",
    "text": " All the kings of the nations, even all of them, lie in glory, every one in his own house.                                                                                                                                                                                                                                                                                                                                                                                                                                                                                                                                                                                                                                                                                                                                                                                                                                                                                                                                              "
  }
]