[
  {
    "id": "1096951655108575233",
    "book": "exodus                             ",
    "chapter": "12",
    "verse": "21",
    "text": "於是，摩西 召了 以色列 的眾 長老來，對他們 說：「你們要按著家口 取 出 羊羔，把這逾越節的羊羔 宰了。                                                                                                                                                                                                                                                                                                                                                                                                                                                                                                                                                                                                                                                                                                                                                                                                                                                                                        "
  }
]