[
  {
    "id": "1138134827178098690",
    "book": "secondsamuel                       ",
    "chapter": "13",
    "verse": "36",
    "text": "Und da er hatte ausgeredet, siehe, da kamen die Kinder des Konigs und huben ihre Stimme auf und weineten. Der Konig und alle seine Knechte weineten auch fast sehr.                                                                                                                                                                                                                                                                                                                                                                                                                                                                                                                                                                                                                                                                                                                                                                                                                                                                     "
  }
]