[
  {
    "id": "888950831070380033",
    "book": "isaiah                             ",
    "chapter": "3",
    "verse": "2",
    "text": "The mighty man, and the man of war, the judge, and the prophet, and the prudent, and the ancient,                                                                                                                                                                                                                                                                                                                                                                                                                                                                                                                                                                                                                                                                                                                                                                                                                                                                                                                                       "
  }
]