[
  {
    "id": "1138146910480826370",
    "book": "amos                               ",
    "chapter": "3",
    "verse": "6",
    "text": "Blaset man auch die Posaune in einer Stadt, da sich das Volk davor nicht entsetze? Ist auch ein Unglück in der Stadt, das der HERR nicht tue?                                                                                                                                                                                                                                                                                                                                                                                                                                                                                                                                                                                                                                                                                                                                                                                                                                                                                          "
  }
]