[
  {
    "id": "888958111568363521",
    "book": "secondCorinthians                  ",
    "chapter": "12",
    "verse": "8",
    "text": "For this thing I besought the Lord thrice, that it might depart from me.                                                                                                                                                                                                                                                                                                                                                                                                                                                                                                                                                                                                                                                                                                                                                                                                                                                                                                                                                                "
  }
]