[
  {
    "id": "1138136108312231938",
    "book": "firstchronicles                    ",
    "chapter": "11",
    "verse": "47",
    "text": "Eliel, Obed, Jaesiel von Mezobaja.                                                                                                                                                                                                                                                                                                                                                                                                                                                                                                                                                                                                                                                                                                                                                                                                                                                                                                                                                                                                      "
  }
]