[
  {
    "id": "1096951953490673665",
    "book": "firstSamuel                        ",
    "chapter": "1",
    "verse": "26",
    "text": "婦人說：「主 啊，我敢在你 面前 起誓，從前在你 這裡 站著 祈求 耶和華 的那婦人，就是我。                                                                                                                                                                                                                                                                                                                                                                                                                                                                                                                                                                                                                                                                                                                                                                                                                                                                                                           "
  }
]