[
  {
    "id": "888953632418856961",
    "book": "ezekiel                            ",
    "chapter": "21",
    "verse": "5",
    "text": "That all flesh may know that I the LORD have drawn forth my sword out of his sheath: it shall not return any more.                                                                                                                                                                                                                                                                                                                                                                                                                                                                                                                                                                                                                                                                                                                                                                                                                                                                                                                      "
  }
]