[
  {
    "id": "1096952357135712257",
    "book": "revelation                         ",
    "chapter": "21",
    "verse": "12",
    "text": "有 高 大 的牆，有 十二個 門， 門 上 有十二位 天使，門 上又 寫著 以色列 十二個 支派 的名字。                                                                                                                                                                                                                                                                                                                                                                                                                                                                                                                                                                                                                                                                                                                                                                                                                                                                                                       "
  }
]